{"cameraMode":{"drawMode":0,"name":"Shaded","section":"Shading Mode"},"sceneLighting":false,"audioPlay":false,"sceneViewState":{"m_AlwaysRefresh":false,"showFog":true,"showSkybox":false,"showFlares":true,"showImageEffects":true,"showParticleSystems":true,"showVisualEffectGraphs":true,"m_FxEnabled":true},"in2DMode":false,"pivot":{"x":7.7377610206604,"y":0.7696163058280945,"z":0.36605608463287356},"rotation":{"x":0.0947604700922966,"y":0.8386001586914063,"z":-0.15467268228530885,"w":0.5136985182762146},"size":1.250514268875122,"orthographic":false}